[
    {
        "Name": "老镇",
        "Value": "156"
    },
    {
        "Name": "新松水库",
        "Value": "195"
    },
    {
        "Name": "黄茅田",
        "Value": "147"
    },
    {
        "Name": "台山百米塔",
        "Value": "175"
    },
    {
        "Name": "钦头村",
        "Value": "179"
    },
    {
        "Name": "广海湾",
        "Value": "152"
    },
    {
        "Name": "长安小学",
        "Value": "152"
    },
    {
        "Name": "赤溪镇",
        "Value": "123"
    },
    {
        "Name": "都斛镇",
        "Value": "129"
    }
]